ipe_client/__init__.py
ipe_client/client.py
ipe_client-1.2.0.dist-info/licenses/LICENSE
ipe_client-1.2.0.dist-info/METADATA
ipe_client-1.2.0.dist-info/WHEEL
ipe_client-1.2.0.dist-info/top_level.txt
ipe_client-1.2.0.dist-info/RECORD
