Metadata-Version: 2.4
Name: ipe-client
Version: 1.2.0
Summary: A modern, asynchronous Python SDK for the IPE API.
Author-email: Tejas Rajesh <tejasr@4gd.ai>
License: MIT License
Project-URL: Homepage, https://github.com/4gd-ai/4gd-image-processing-engine-SDK
Project-URL: Bug Tracker, https://github.com/your-username/ipe-python-sdk/issues
Keywords: ipe,api,sdk,async,client
Classifier: Programming Language :: Python :: 3
Classifier: License :: OSI Approved :: MIT License
Classifier: Operating System :: OS Independent
Classifier: Development Status :: 4 - Beta
Classifier: Intended Audience :: Developers
Classifier: Framework :: AsyncIO
Requires-Python: >=3.9
License-File: LICENSE
Requires-Dist: httpx>=0.23.0
Dynamic: license-file
